saigen_dep_test/__init__.py
saigen_dep_test/script.py
saigen_dep_test-0.2.data/scripts/script.py
saigen_dep_test-0.2.dist-info/METADATA
saigen_dep_test-0.2.dist-info/WHEEL
saigen_dep_test-0.2.dist-info/top_level.txt
saigen_dep_test-0.2.dist-info/RECORD
