Metadata-Version: 2.1
Name: saigen-dep-test
Version: 0.2
Summary: A test of using dependencies
Author: Francois
Author-email: francois@saigen.co.za
Classifier: Programming Language :: Python :: 3
Classifier: License :: OSI Approved :: MIT License
Classifier: Operating System :: OS Independent
Requires-Dist: boto3
Requires-Dist: requests
Requires-Dist: librosa
Requires-Dist: soundfile
